{
  "storeInfo": {
    "name": "lorem name",
    "logo": "lorem logo",
    "logoUrl": "/assets/logo.svg",
    "slogan": "lorem Slogan",
    "shortDescription": "Lorem ipsum dolor sit amet consectetur adipisicing elit. Repellendus sit amet quia vero incidunt. Omnis nobis assumenda explicabo dolor, hic magni provident. Architecto, quisquam? Velit enim quis delectus? Necessitatibus iure!"
  },

  "social": {
    "facebook": "https://facebook.com/yourpage",
    "instagram": "https://instagram.com/yourpage",
    "tiktok": "https://tiktok.com/@yourpage",
    "whatsapp": "https://wa.me/yourNumber"
  }
}
